LICENSE
MANIFEST.in
NEWS.txt
README.rst
setup.py
src/shuttle/__init__.py
src/shuttle/sync.py
src/shuttle/transifex.py
src/shuttle.egg-info/PKG-INFO
src/shuttle.egg-info/SOURCES.txt
src/shuttle.egg-info/dependency_links.txt
src/shuttle.egg-info/entry_points.txt
src/shuttle.egg-info/not-zip-safe
src/shuttle.egg-info/requires.txt
src/shuttle.egg-info/top_level.txt