Metadata-Version: 1.0
Name: shuttle
Version: 0.8
Summary: A command-line interface for moving content between help desk and translation systems
Home-page: http://github.com/eventbrite/localization_shuttle
Author: Nathan Yergler
Author-email: nathan@eventbrite.com
License: Apache License v2
Platform: UNKNOWN
